README.rst
setup.py
lgcy_utils/__init__.py
lgcy_utils/address.py
lgcy_utils/conversions.py
lgcy_utils/currency.py
lgcy_utils/decorators.py
lgcy_utils/encoding.py
lgcy_utils/hexadecimal.py
lgcy_utils/types.py
lgcy_utils.egg-info/PKG-INFO
lgcy_utils.egg-info/SOURCES.txt
lgcy_utils.egg-info/dependency_links.txt
lgcy_utils.egg-info/not-zip-safe
lgcy_utils.egg-info/requires.txt
lgcy_utils.egg-info/top_level.txt
lgcy_utils/typing/__init__.py
lgcy_utils/typing/misc.py