Metadata-Version: 1.2
Name: lgcy-utils
Version: 1.0.4
Summary: Common utility functions for legacy codebases.
Home-page: https://github.com/autotheos/lgcy-utils
Author: Shamsudin Serderov
Author-email: iexbase@protonmail.com
License: MIT
Platform: UNKNOWN
Classifier: Intended Audience :: Developers
Classifier: License :: OSI Approved :: MIT License
Classifier: Natural Language :: English
Classifier: Programming Language :: Python :: 3
Classifier: Programming Language :: Python :: 3.6
Classifier: Programming Language :: Python :: 3.7
Requires-Python: >=3.5,!=3.5.2,<4
